{
	"name": "PatientDataIngestion",
	"properties": {
		"activities": [
			{
				"name": "SetDestinationVariable",
				"type": "SetVariable",
				"dependsOn": [],
				"policy": {
					"secureOutput": false,
					"secureInput": false
				},
				"userProperties": [],
				"typeProperties": {
					"variableName": "Destination",
					"value": {
						"value": "@concat('bronze/patient', '/', formatDateTime(utcnow(), 'yyyy'), '/',formatDateTime(utcnow(),'MM'),'/',formatDateTime(utcnow(),'dd'), '/', pipeline().parameters.triggerFileName)\n",
						"type": "Expression"
					}
				}
			},
			{
				"name": "CopyFromSourceToBronze",
				"type": "Copy",
				"dependsOn": [
					{
						"activity": "SetDestinationVariable",
						"dependencyConditions": [
							"Succeeded"
						]
					}
				],
				"policy": {
					"timeout": "0.12:00:00",
					"retry": 0,
					"retryIntervalInSeconds": 30,
					"secureOutput": false,
					"secureInput": false
				},
				"userProperties": [],
				"typeProperties": {
					"source": {
						"type": "JsonSource",
						"storeSettings": {
							"type": "AzureBlobStorageReadSettings",
							"fileListPath": "patient-data-source/patient-01.json",
							"enablePartitionDiscovery": false
						},
						"formatSettings": {
							"type": "JsonReadSettings"
						}
					},
					"sink": {
						"type": "JsonSink",
						"storeSettings": {
							"type": "AzureBlobFSWriteSettings"
						},
						"formatSettings": {
							"type": "JsonWriteSettings"
						}
					},
					"enableStaging": false
				},
				"inputs": [
					{
						"referenceName": "SourceDataSet",
						"type": "DatasetReference",
						"parameters": {
							"file": "@trigger().outputs.body.fileName"
						}
					}
				],
				"outputs": [
					{
						"referenceName": "PatientDataBronzeDataSet",
						"type": "DatasetReference",
						"parameters": {
							"destination": "@variables('Destination')"
						}
					}
				]
			}
		],
		"parameters": {
			"triggerFileName": {
				"type": "string",
				"defaultValue": "@trigger().outputs.body.fileName"
			},
			"destination": {
				"type": "string",
				"defaultValue": "@variables('Destination')"
			}
		},
		"variables": {
			"TriggerFileName": {
				"type": "String"
			},
			"Destination": {
				"type": "String"
			}
		},
		"annotations": []
	}
}